AUTHORS
README
setup.py
django_inplaceedit_version1.egg-info/PKG-INFO
django_inplaceedit_version1.egg-info/SOURCES.txt
django_inplaceedit_version1.egg-info/dependency_links.txt
django_inplaceedit_version1.egg-info/not-zip-safe
django_inplaceedit_version1.egg-info/top_level.txt
inplaceeditform/__init__.py
inplaceeditform/commons.py
inplaceeditform/install.txt
inplaceeditform/models.py
inplaceeditform/urls.py
inplaceeditform/views.py
inplaceeditform/media/inplaceeditform/css/style.css
inplaceeditform/media/inplaceeditform/img/apply.gif
inplaceeditform/media/inplaceeditform/img/cancel.gif
inplaceeditform/media/inplaceeditform/js/DateTimeShortcuts2.js
inplaceeditform/media/inplaceeditform/js/inplaceeditform.js
inplaceeditform/media/inplaceeditform/js/jquery.json.js
inplaceeditform/templates/inplace_edit.html
inplaceeditform/templates/inplace_media.html
inplaceeditform/templatetags/__init__.py
inplaceeditform/templatetags/inplace_edit.py