Metadata-Version: 1.0
Name: django-inplaceedit-version1
Version: 0.55
Summary: Django application that allows you to inline edition of some data from the database
Home-page: https://tracpub.yaco.es/djangoapps/wiki/InplaceEditForm
Author: Yaco Sistemas S.L.
Author-email: pmartin@yaco.es
License: LGPL 3
Keywords: django inplace inline edit inline form
Platform: UNKNOWN
Classifier: Development Status :: 4 - Beta
Classifier: Framework :: Django
Classifier: License :: OSI Approved :: GNU Library or Lesser General Public License (LGPL)
